sunmao/__init__.py
sunmao/mortise_tenson.py
sunmao-0.5.1.dist-info/METADATA
sunmao-0.5.1.dist-info/WHEEL
sunmao-0.5.1.dist-info/licenses/LICENSE
sunmao-0.5.1.dist-info/RECORD
