Metadata-Version: 2.4
Name: sunmao
Version: 0.5.1
Summary: A flexible subplot layout library for matplotlib with support for adding panels in all directions
License: MIT
License-File: LICENSE
Keywords: matplotlib,visualization,subplot,layout,plotting
Author: seqyuan
Author-email: seqyuan@example.com
Requires-Python: >=3.9,<4.0
Classifier: Development Status :: 4 - Beta
Classifier: Intended Audience :: Science/Research
Classifier: License :: OSI Approved :: MIT License
Classifier: Operating System :: OS Independent
Classifier: Programming Language :: Python :: 3
Classifier: Programming Language :: Python :: 3.9
Classifier: Programming Language :: Python :: 3.10
Classifier: Programming Language :: Python :: 3.11
Classifier: Programming Language :: Python :: 3.12
Classifier: Programming Language :: Python :: 3.13
Classifier: Programming Language :: Python :: 3.14
Classifier: Topic :: Scientific/Engineering :: Visualization
Classifier: Topic :: Software Development :: Libraries :: Python Modules
Requires-Dist: matplotlib (>=3.5.0,<4.0.0)
Requires-Dist: numpy (>=1.21.0,<2.0.0)
Project-URL: Documentation, https://sunmao.readthedocs.io
Project-URL: Homepage, https://github.com/seqyuan/sunmao
Project-URL: Repository, https://github.com/seqyuan/sunmao
